minimum/__init__.py
minimum/findmin.py
minimum-1.0.dist-info/LICENSE
minimum-1.0.dist-info/METADATA
minimum-1.0.dist-info/WHEEL
minimum-1.0.dist-info/top_level.txt
minimum-1.0.dist-info/RECORD
