Metadata-Version: 2.1
Name: minimum
Version: 1.0
Summary: A package which find minimum from given vector
Home-page: UNKNOWN
Author: Chandni Patel
Author-email: chandnip445@gmail.com
License: UNKNOWN
Platform: UNKNOWN
Classifier: Programming Language :: Python :: 3
Classifier: License :: OSI Approved :: MIT License
Classifier: Operating System :: OS Independent
